README.md
setup.cfg
setup.py
picaf/__init__.py
picaf/file_finder.py
picaf/main.py
picaf.egg-info/PKG-INFO
picaf.egg-info/SOURCES.txt
picaf.egg-info/dependency_links.txt
picaf.egg-info/entry_points.txt
picaf.egg-info/requires.txt
picaf.egg-info/top_level.txt
tests/__init__.py
tests/test_file_finder.py